{"namedChunkGroups":{"polyfill":{"name":"polyfill","assets":[{"name":"webpack-runtime-bb1417821e1b08ad2a4d.js","size":5859},{"name":"polyfill-9297e683e8587f367349.js","size":85308}],"filteredAssets":0,"assetsSize":91167,"filteredAuxiliaryAssets":2,"auxiliaryAssetsSize":229353},"app":{"name":"app","assets":[{"name":"webpack-runtime-bb1417821e1b08ad2a4d.js","size":5859},{"name":"framework-5b465e8ce79b37b812d9.js","size":129847},{"name":"b5f2ed29-ebc83b4a29415b01e447.js","size":258843},{"name":"app-12340faf79dbffb55d3a.js","size":108890}],"filteredAssets":0,"assetsSize":503439,"filteredAuxiliaryAssets":4,"auxiliaryAssetsSize":1839172},"component---src-pages-404-js":{"name":"component---src-pages-404-js","assets":[{"name":"component---src-pages-404-js-3ec4b0ce4f1b8228f507.js","size":426}],"filteredAssets":0,"assetsSize":426,"filteredAuxiliaryAssets":1,"auxiliaryAssetsSize":448},"component---src-pages-index-js":{"name":"component---src-pages-index-js","assets":[{"name":"styles.c24982db006ceaca26cd.css","size":146649},{"name":"component---src-pages-index-js-e455bf28684d1405afb4.js","size":6260}],"filteredAssets":0,"assetsSize":152909,"filteredAuxiliaryAssets":47,"auxiliaryAssetsSize":995601},"component---src-templates-blogpost-js":{"name":"component---src-templates-blogpost-js","assets":[{"name":"styles.c24982db006ceaca26cd.css","size":146649},{"name":"component---src-templates-blogpost-js-425825fe8468075ad36b.js","size":66366}],"filteredAssets":0,"assetsSize":213015,"filteredAuxiliaryAssets":47,"auxiliaryAssetsSize":1285241}},"assetsByChunkName":{"polyfill":["webpack-runtime-bb1417821e1b08ad2a4d.js","polyfill-9297e683e8587f367349.js"],"app":["webpack-runtime-bb1417821e1b08ad2a4d.js","framework-5b465e8ce79b37b812d9.js","b5f2ed29-ebc83b4a29415b01e447.js","app-12340faf79dbffb55d3a.js"],"component---src-pages-404-js":["component---src-pages-404-js-3ec4b0ce4f1b8228f507.js"],"component---src-pages-index-js":["styles.c24982db006ceaca26cd.css","component---src-pages-index-js-e455bf28684d1405afb4.js"],"component---src-templates-blogpost-js":["styles.c24982db006ceaca26cd.css","component---src-templates-blogpost-js-425825fe8468075ad36b.js"]},"childAssetsByChunkName":{}}